cupid_matching/.DS_Store
cupid_matching/.idea/.gitignore
cupid_matching/.idea/cupid_matching.iml
cupid_matching/.idea/inspectionProfiles/Project_Default.xml
cupid_matching/.idea/inspectionProfiles/profiles_settings.xml
cupid_matching/.idea/misc.xml
cupid_matching/.idea/modules.xml
cupid_matching/.idea/vcs.xml
cupid_matching/__init__.py
cupid_matching/choo_siow.py
cupid_matching/choo_siow_gender_heteroskedastic.py
cupid_matching/choo_siow_heteroskedastic.py
cupid_matching/choo_siow_no_singles.py
cupid_matching/cupid_streamlit.py
cupid_matching/cupid_streamlit_utils.py
cupid_matching/entropy.py
cupid_matching/example_choo_siow.py
cupid_matching/example_choo_siow_no_singles.py
cupid_matching/example_nested_logit.py
cupid_matching/ipfp_solvers.py
cupid_matching/matching_utils.py
cupid_matching/min_distance.py
cupid_matching/min_distance_utils.py
cupid_matching/model_classes.py
cupid_matching/mypy.ini
cupid_matching/nested_logit.py
cupid_matching/poisson_glm.py
cupid_matching/poisson_glm_utils.py
cupid_matching/utils.py
cupid_matching-1.3.dist-info/METADATA
cupid_matching-1.3.dist-info/WHEEL
cupid_matching-1.3.dist-info/RECORD
