Metadata-Version: 2.1
Name: cupid_matching
Version: 1.3
Summary: Solves, simulates, and estimates separable matching TU models
Author: Bernard Salanie
Author-email: bsalanie@columbia.edu
Requires-Python: >=3.10,<4.0
Classifier: Programming Language :: Python :: 3
Classifier: Programming Language :: Python :: 3.10
Classifier: Programming Language :: Python :: 3.11
Requires-Dist: altair (>=4.2,<5.0)
Requires-Dist: bs_python_utils (>=0.6,<0.7)
Requires-Dist: matplotlib (>=3.6,<4.0)
Requires-Dist: numpy (>=1.20,<2.0)
Requires-Dist: pandas (>=2.1,<3.0)
Requires-Dist: pre-commit (>=3.5.0,<4.0.0)
Requires-Dist: scikit-learn (>=1.1,<2.0)
Requires-Dist: scipy (>=1.8,<2.0)
Requires-Dist: seaborn (>=0.12,<0.13)
Requires-Dist: streamlit (>=1.20,<2.0)
Requires-Dist: watchdog (>=3.0,<4.0)
